dakb_client/__init__.py
dakb_client/async_client.py
dakb_client/client.py
dakb_client/exceptions.py
dakb_client/mcp_client.py
dakb_client/models.py
dakb_client/py.typed
dakb_client-1.0.2.dist-info/METADATA
dakb_client-1.0.2.dist-info/WHEEL
dakb_client-1.0.2.dist-info/top_level.txt
dakb_client-1.0.2.dist-info/RECORD
