Metadata-Version: 2.4
Name: dakb-client
Version: 1.0.2
Summary: Python client SDK for DAKB (Distributed Agent Knowledge Base)
Author: oracleseed
License-Expression: MIT
Project-URL: Homepage, https://github.com/oracleseed/dakb
Project-URL: Documentation, https://github.com/oracleseed/dakb/tree/main/docs
Project-URL: Repository, https://github.com/oracleseed/dakb
Keywords: dakb,mcp,agent,knowledge-base,ai
Classifier: Development Status :: 4 - Beta
Classifier: Intended Audience :: Developers
Classifier: Operating System :: OS Independent
Classifier: Programming Language :: Python :: 3
Classifier: Programming Language :: Python :: 3.10
Classifier: Programming Language :: Python :: 3.11
Classifier: Programming Language :: Python :: 3.12
Classifier: Topic :: Software Development :: Libraries :: Python Modules
Classifier: Typing :: Typed
Requires-Python: >=3.10
Requires-Dist: httpx>=0.25.0
Requires-Dist: pydantic>=2.0.0
Provides-Extra: dev
Requires-Dist: pytest>=7.0.0; extra == "dev"
Requires-Dist: pytest-asyncio>=0.21.0; extra == "dev"
Requires-Dist: pytest-httpx>=0.22.0; extra == "dev"
Requires-Dist: mypy>=1.0.0; extra == "dev"
Requires-Dist: ruff>=0.1.0; extra == "dev"
